esextract.py
esextract-0.0.1.dist-info/METADATA
esextract-0.0.1.dist-info/WHEEL
esextract-0.0.1.dist-info/top_level.txt
esextract-0.0.1.dist-info/RECORD
